LICENSE.md
MANIFEST.in
README.md
requirements.txt
setup.cfg
setup.py
pyconverge/ArgumentParser.py
pyconverge/BaseClassLoader.py
pyconverge/ConfigValidator.py
pyconverge/__init__.py
pyconverge/__main__.py
pyconverge/converge.py
pyconverge.egg-info/PKG-INFO
pyconverge.egg-info/SOURCES.txt
pyconverge.egg-info/dependency_links.txt
pyconverge.egg-info/entry_points.txt
pyconverge.egg-info/requires.txt
pyconverge.egg-info/top_level.txt
pyconverge/plugins/BasePlugin.py
pyconverge/plugins/__init__.py
pyconverge/plugins/properties/FilterTargets.py
pyconverge/plugins/properties/LoadDataFromDisk.py
pyconverge/plugins/properties/LoadHierarchy.py
pyconverge/plugins/properties/LoadTargets.py
pyconverge/plugins/properties/OutputProperties.py
pyconverge/plugins/properties/PrintData.py
pyconverge/plugins/properties/WriteTargets.py
pyconverge/plugins/properties/__init__.py
pyconverge/resources/etc/converge.yaml.template
pyconverge/resources/repository/data/default/app/.gitkeep
pyconverge/resources/repository/data/default/shared/.gitkeep
pyconverge/resources/repository/hierarchy/hierarchy.yaml
pyconverge/resources/repository/targets/hosts/.gitkeep
pyconverge/resources/repository/targets/mapping/.gitkeep
pyconverge/schemas/application_schema.yaml
pyconverge/schemas/converge_schema.yaml
pyconverge/schemas/hierarchy_schema.yaml
pyconverge/schemas/host_schema.yaml
tests/test_ArgumentParser.py
tests/test_FilterTargets.py
tests/test_Helpers.py
tests/test_LoadTargets.py
tests/test_PrintData.py
tests/test_RepositoryReader.py
tests/test_converge.py
tests/resources/etc/converge.yaml
tests/resources/repository/test.py
tests/resources/repository/data/default/app/application1/propfile1.properties
tests/resources/repository/data/default/app/application1/host/pre-host2/propfile1.properties
tests/resources/repository/data/default/app/application1/mapping/dependencies.yaml
tests/resources/repository/data/default/app/application2/propfile1.properties
tests/resources/repository/data/default/app/application2/mapping/dependencies.yaml
tests/resources/repository/data/default/app/application3/propfile4.properties
tests/resources/repository/data/default/app/application3/mapping/dependencies.yaml
