Metadata-Version: 1.1
Name: pyconverge
Version: 0.0.18
Summary: Resolve configurations from abstract hierarchies and templates
Home-page: https://github.com/drewboswell/converge
Author: Andrew Boswell
Author-email: drewboswell@gmail.com
License: Apache License 2.0
Keywords: configuration management development operations system sysadmin config converge
Platform: any
Classifier: Programming Language :: Python
Classifier: Programming Language :: Python :: 3
Classifier: Programming Language :: Python :: 3.5
Classifier: Programming Language :: Python :: 3.6
Classifier: Programming Language :: Python :: Implementation :: CPython
Classifier: Programming Language :: Python :: Implementation :: PyPy
Classifier: Development Status :: 1 - Planning
Classifier: Intended Audience :: Developers
Classifier: Intended Audience :: System Administrators
Classifier: Intended Audience :: Financial and Insurance Industry
Classifier: Operating System :: OS Independent
Classifier: Topic :: Office/Business
